tours/__init__.py
tours/admin.py
tours/apps.py
tours/forms.py
tours/models.py
tours/settings.py
tours/tests.py
tours/urls.py
tours/utils.py
tours/views.py
tours/migrations/0001_initial.py
tours/migrations/__init__.py
tours/templates/tours/tags/tours.html
tours/templatetags/__init__.py
tours/templatetags/tours.py
django_tours-1.1.1.dist-info/LICENSE
django_tours-1.1.1.dist-info/METADATA
django_tours-1.1.1.dist-info/WHEEL
django_tours-1.1.1.dist-info/top_level.txt
django_tours-1.1.1.dist-info/RECORD
